Workbook

Sheet  OLD HR AND ADMIN BUDGET
B2: SohCahToa Holdings Departmental Template
B3: HR and Admin Budget
B4: Expense Heads | C4: January | D4: February | E4: March | F4: April | G4: May | H4: June | I4: July | J4: August | K4: September | L4: October | M4: November | N4: December | O4: Total
B5: Rent | C5: ='Input Worksheet'!C49 -> 0 | D5: ='Input Worksheet'!D49 -> 0 | E5: ='Input Worksheet'!E49 -> 34900000 | F5: ='Input Worksheet'!F49 -> 0 | G5: ='Input Worksheet'!G49 -> 0 | H5: ='Input Worksheet'!H49 -> 21861657 | I5: ='Input Worksheet'!I49 -> 0 | J5: ='Input Worksheet'!J49 -> 0 | ... N5: ='Input Worksheet'!N49 -> 4492800 | O5: =SUM(C5:N5) -> 64710457
B6: Birthday Gifts | C6: ='Input Worksheet'!C54 -> 40000 | D6: 40000 | E6: ='Input Worksheet'!E54 -> 240000 | F6: ='Input Worksheet'!F54 -> 40000 | G6: ='Input Worksheet'!G54 -> 80000 | H6: ='Input Worksheet'!H54 -> 80000 | I6: ='Input Worksheet'!I54 -> 80000 | J6: ='Input Worksheet'!J54 -> 280000 | K6: ='Input Worksheet'!K54 -> 400000 | L6: ='Input Worksheet'!L54 -> 120000 | ... N6: ='Input Worksheet'!N54 -> 80000 | O6: =SUM(C6:N6) -> 1880000
B7: Communication | C7: ='Input Worksheet'!#REF! -> #REF! | D7: ='Input Worksheet'!#REF! -> #REF! | E7: ='Input Worksheet'!#REF! -> #REF! | F7: ='Input Worksheet'!#REF! -> #REF! | G7: ='Input Worksheet'!#REF! -> #REF! | H7: ='Input Worksheet'!#REF! -> #REF! | I7: ='Input Worksheet'!#REF! -> #REF! | J7: ='Input Worksheet'!#REF! -> #REF! | ... N7: ='Input Worksheet'!#REF! -> #REF! | O7: =SUM(C7:N7) -> #REF!
B8: Insurance | C8: ='Input Worksheet'!C28 -> 7042958.1 | D8: ='Input Worksheet'!D28 -> 5146814.6 | E8: ='Input Worksheet'!E28 -> 3355941.4 | F8: ='Input Worksheet'!F28 -> 3853173.4 | G8: ='Input Worksheet'!G28 -> 843380.87 | H8: ='Input Worksheet'!H28 -> 8073232 | I8: ='Input Worksheet'!I28 -> 4177173.4 | J8: ='Input Worksheet'!J28 -> 0 | ... N8: ='Input Worksheet'!N28 -> 8600000 | O8: =SUM(C8:N8) -> 49440764
B9: Repairs and Maintenance | C9: ='Input Worksheet'!C42 -> 405000 | D9: ='Input Worksheet'!D42 -> 300000 | E9: ='Input Worksheet'!E42 -> 621000 | F9: ='Input Worksheet'!F42 -> 500000 | G9: ='Input Worksheet'!G42 -> 500000 | H9: ='Input Worksheet'!H42 -> 800000 | I9: ='Input Worksheet'!I42 -> 500000 | J9: ='Input Worksheet'!J42 -> 542000 | ... N9: ='Input Worksheet'!N42 -> 1750000 | O9: =SUM(C9:N9) -> 8481000
B10: Fuelling | C10: ='Input Worksheet'!C61 -> 2800000 | D10: ='Input Worksheet'!D61 -> 3000000 | E10: ='Input Worksheet'!E61 -> 3070000 | F10: ='Input Worksheet'!F61 -> 3499600 | G10: ='Input Worksheet'!G61 -> 3499600 | H10: ='Input Worksheet'!H61 -> 3569600 | I10: ='Input Worksheet'!I61 -> 4124000.1 | J10: ='Input Worksheet'!J61 -> 4904375.3 | ... N10: ='Input Worksheet'!N61 -> 7168634.4 | O10: =SUM(C10:N10) -> 55782767
B11: Travelling Expense | C11: ='Input Worksheet'!C92 -> 7000000 | D11: ='Input Worksheet'!D92 -> 7000000 | E11: ='Input Worksheet'!E92 -> 7000000 | F11: ='Input Worksheet'!F92 -> 16600000 | G11: ='Input Worksheet'!G92 -> 16600000 | H11: ='Input Worksheet'!H92 -> 16600000 | I11: ='Input Worksheet'!I92 -> 32200000 | J11: ='Input Worksheet'!J92 -> 32200000 | ... N11: ='Input Worksheet'!N92 -> 47800000 | O11: =SUM(C11:N11) -> 310800000
B12: Team Bonding | C12: ='Input Worksheet'!C66 -> 897000 | D12: ='Input Worksheet'!D66 -> 975000 | E12: ='Input Worksheet'!E66 -> 2757000 | F12: ='Input Worksheet'!F66 -> 1209000 | G12: ='Input Worksheet'!G66 -> 1209000 | H12: ='Input Worksheet'!H66 -> 3054000 | I12: ='Input Worksheet'!I66 -> 1326000 | J12: ='Input Worksheet'!J66 -> 1326000 | ... N12: ='Input Worksheet'!N66 -> 1326000 | O12: =SUM(C12:N12) -> 20037000
B13: General office Expenses | C13: ='Input Worksheet'!C72 -> 603417.62 | D13: ='Input Worksheet'!D72 -> 588432 | E13: ='Input Worksheet'!E72 -> 1465052.3 | F13: ='Input Worksheet'!F72 -> 953259.84 | G13: ='Input Worksheet'!G72 -> 1211388.8 | H13: ='Input Worksheet'!H72 -> 1348444.4 | I13: ='Input Worksheet'!I72 -> 1480432.7 | J13: ='Input Worksheet'!J72 -> 1268788.8 | ... N13: ='Input Worksheet'!N72 -> 1522288.8 | O13: =SUM(C13:N13) -> 15060112
B14: Transportation | D14: 50000 | E14: 50000 | F14: 50000 | G14: 50000 | H14: 50000 | I14: 50000 | J14: 50000 | K14: 50000 | L14: 50000 | M14: 50000 | N14: 50000 | O14: =SUM(C14:N14) -> 550000
B15: Training and Team building | C15: ='Input Worksheet'!C76 -> 30000000 | D15: ='Input Worksheet'!D76 -> 0 | E15: ='Input Worksheet'!E76 -> 0 | F15: ='Input Worksheet'!F76 -> 0 | G15: ='Input Worksheet'!G76 -> 0 | H15: ='Input Worksheet'!H76 -> 0 | I15: ='Input Worksheet'!I76 -> 0 | J15: ='Input Worksheet'!J76 -> 0 | ... N15: ='Input Worksheet'!N76 -> 0 | O15: =SUM(C15:N15) -> 30000000
B16: Staff Events | C16: ='Input Worksheet'!C81 -> 0 | D16: ='Input Worksheet'!D81 -> 0 | E16: ='Input Worksheet'!E81 -> 0 | F16: ='Input Worksheet'!F81 -> 0 | G16: ='Input Worksheet'!G81 -> 0 | H16: ='Input Worksheet'!H81 -> 0 | I16: ='Input Worksheet'!I81 -> 0 | J16: ='Input Worksheet'!J81 -> 0 | ... N16: ='Input Worksheet'!N81 -> 25800000 | O16: =SUM(C16:N16) -> 29919615
B17: Sports and Fitness | C17: ='Input Worksheet'!C35 -> 2365333.3 | D17: ='Input Worksheet'!D35 -> 2311333.3 | E17: ='Input Worksheet'!E35 -> 2661333.3 | F17: ='Input Worksheet'!F35 -> 3287086 | G17: ='Input Worksheet'!G35 -> 3179086 | H17: ='Input Worksheet'!H35 -> 3179086 | I17: ='Input Worksheet'!I35 -> 3413006.6 | J17: ='Input Worksheet'!J35 -> 3305006.6 | ... N17: ='Input Worksheet'!N35 -> 3462382.3 | O17: =SUM(C17:N17) -> 37393425
B18: Personnel Cost | C18: ='Input Worksheet'!C21 -> 13641222 | D18: ='Input Worksheet'!D21 -> 16237204 | E18: ='Input Worksheet'!E21 -> 27949214 | F18: ='Input Worksheet'!F21 -> 26994693 | G18: ='Input Worksheet'!G21 -> 18287995 | H18: ='Input Worksheet'!H21 -> 32768566 | I18: ='Input Worksheet'!I21 -> 38459526 | J18: ='Input Worksheet'!J21 -> 20303065 | ... N18: ='Input Worksheet'!N21 -> 64597783 | O18: =SUM(C18:N18) -> 3.5050137e+08
B19: Capital Expenditure | C19: ='Capital Expenditure'!C9 -> 0 | D19: ='Capital Expenditure'!D9 -> 0 | E19: ='Capital Expenditure'!E9 -> 0 | F19: ='Capital Expenditure'!F9 -> 0 | G19: ='Capital Expenditure'!G9 -> 0 | H19: ='Capital Expenditure'!H9 -> 0 | I19: ='Capital Expenditure'!I9 -> 0 | J19: ='Capital Expenditure'!J9 -> 0 | ... N19: ='Capital Expenditure'!N9 -> 0 | O19: =SUM(C19:N19) -> 0
B20: Total | C20: =SUM(C5:C19) -> #REF! | D20: =SUM(D5:D19) -> #REF! | E20: =SUM(E5:E19) -> #REF! | F20: =SUM(F5:F19) -> #REF! | G20: =SUM(G5:G19) -> #REF! | H20: =SUM(H5:H19) -> #REF! | I20: =SUM(I5:I19) -> #REF! | J20: =SUM(J5:J19) -> #REF! | ... O20: =SUM(O5:O19) -> #REF!
F26: =SUM(F17:K17) -> 19668278

Sheet Comments and Notes (2)Old
C3: The 30% inflation rate forecasted is based on KPMG's inflation forecast for 2024
C5: Communication Expense | D5: Comments/Note
C6: Airtime and Data | D6: This is based on a credit limit of #10,000 for 27 staff per month
C7: CUG Subscription | D7: The cost is #1,000 per line. This amount would be paid at the end of the year for all lines for 1 year
C8: Office Internet | D8: The monthly cost of internet ( hyperia) is #215,000 and this is prepaid quarterly. This cost was inflated by 30% for the first 2 quarters and then by another 10%.
C9: Total
C11: Personnel Expenses
C12: Salaries and Allowance | D12: The current salary amount is based on the newly approved salary review structure for all existing roles
C13: Leave Allowance | D13: This is 10% of the annual basic salary payable at each employees work anniversary
C14: Bonus | D14: The maximum performance bonus is 75% for each quarter, which is paid in the following month
C15: 13th Month Salary | D15: 100% of employee gross salary payable in December
C16: Promotion | D16: A 25% increment was factored into this computation
C17: Staff end of the year package | D17: 1 bag of rice @ #58,000 for one person, half bag of rice@ #30,000 for 27 people, 10 liters oil @ #20,000 for 1 person, 5 liters oil @ #10,000 for 4 people and 3.5 liters oil @ #6,000 for 22 staff. Inflation of 30% is factored and this brings it to #1,149,600.
C18: Staff Training and development | D18: The budget is #100,000 per employee for each quarter, The total is the cost for 27 employees for 4 quarters
C19: New Staff Salary | D19: This is based on their roles and the proposed new salary structure
C20: Bonus for new staff | D20: The 9 new staff will be eligible to bonus. This will be paid only upon confirmation.
C21: Long service award | D21: Company's budget is #1,100,000 and there are 5 eligible staff in 2024
C22: Employer's Pension | D22: This is 10% of the BTH of all employees salary payable monthly
C23: Employer's Pension (New Staff) | D23: This is 10% of BHT of new staff
... C29: gency | D29: The sum of N3,000,000 is projected to cover gratuity for exiting staff and any other related cost.
C30: Total
C32: Insurance
C33: Hmo | D33: 2 platinum plan @ #570,236, 62 sliver plan @ #99,873 all employees and dependants including 9 new staff with 3 dependants each
C34: Group Life | D34: The premium for 27 employees would be #2, 223,817.27. An inflation rate of 30% was factored in
C35: Fire & Buglary | D35: The premium is #271,823
C36: Vehicle | D36: The insurance for the pool car is due in February and Stallion MG is due in December
C37: Total
C40: Sport and Fitness
C41: Field usage and aerobics | D41: The field costs a total of #1,440,000 @ #4,000 for 20 players twice a month #160,000 for 12 months(1,920,000), while aerobics cost 100,000 per month (1,200,000)bringin the total to #3,120,000. A 30% inflation rate was also factored in.
C42: Entertainment | D42: The current cost of refreshment is #109,240 per session and session would hold twice a month and 30% inflation rate was factored
C43: Players Logistics | D43: Players get #4,000 for logistics. Usually, about 10 players train per session and we have 2 sessions in a month. This briings the total to 80,000 per month. However, we project that the number of players may increase by at most 5 players which brings the total to 100,000
C44: Total
C47: Repairs and Maintenance
C48: Vehicle Repairs | D48: This is based on the repairs done in 2023 and porated through out the year, as specific time can not be determined
C49: Motor vehicle renewal | D49: When license would be renewed @ #25,000 each when due as stated in the input worksheet
C50: Vehicle Maintance | D50: The vehicles are serviced every 3 months @ #53,6000 each
C51: Total
C54: Rent Related
C55: Annual Rent | D55: Company rent is due in May 2024, and it would be renewed for two year
C56: Sevice charges (annually) | D56: The service charge remains the same
C57: Electricity supply charges (Quarterly ) | D57: Our current usage per quarter is #2,348,251.41 and 20,30,40,50% inflation rate quarterly was factored
C58: Total
C61: Birthday Gift
C62: Staff Gift | D62: The Company celebrates all staff birthdays by gifting the celebrant a birthday cake within the budget sum of 20,000. An analysis of all staff birthdays for 2024 was done with 7 new staff included for 2024.
C63: Total
C65: Fuelling
C66: Pool Car | D66: The pool car is fueled with #80,000 monthly and 30% inflation rate was factored for the first quarter and a further 10% iinflation for each subsequent quarter
C67: MD's Car | D67: MD's car is fueled with #80,000 monthly and 30% inflation rate was factored for the first quarter and a further 10% iinflation for each subsequent quarter
C68: BM's Car | D68: The fuel allowance for the BM's vechicle is #60,000 and 30% inflation rate was factored for the first quarter ans a further 10% inflation for each quarter
C69: Total
C71: Team Bonding
C72: Weekly Lunch | D72: This is #3,000 for 27 employees every Friday
C73: Quarterly Team Bonding | D73: This is #25,000 for 27 employees every last Friday of the quarter
C74: Total
C76: General Office Expense
C77: Stationery | D77: The cost for 27 employees and 30% inflation rate was factored
C78: Printables | D78: This includes printing of 100 deal slips @ #170,000, 100 Requisition forms @ #120,000, 100 Letter head @#35,000, 100 Envelop @#75,000 and ID card @ #2,500 each
C79: Office supplies and Provisions | D79: The cost for 29 employees is and a 30% inflation rate quarterly was factored
C80: Total
C82: Training and Team Building
C83: Strategy Retreat | D83: The BM and management staff would facilitate the session, the cost is mainly for accomodation and welfare.
C84: Total
C86: Staff Event
C87: Staff end of the year Party | D87: This was projected based on the 2023 budget with the inflation rate factored in
C88: Total
C90: Funmigation | D90: This is done Bi-annually. A mark up was done
C92: Travelling Expenses
C93: Flight Ticket | D93: Based on the trips in 2023 and 30% inflation rate was factored
C94: Hotel and Reservations | D94: Based on the trips in 2023 and 30% inflation rate was factored
C95: Logistics | D95: Based on the trips in 2023 and 30% inflation rate was factored
C96: Feeding | D96: Based on the trips in 2023 and 30% inflation rate was factored

Sheet Input Worksheet (2) Old
C1: January | D1: February | E1: March | F1: April | G1: May | H1: June | I1: July | J1: August | K1: September | L1: October | M1: November | N1: December | O1: Total
B2: Communication Expense
B3: Airtime and Data | C3: =270000*1.3 -> 351000 | D3: =270000*1.3 -> 351000 | E3: =270000*1.3 -> 351000 | F3: =C3*1.1 -> 386100 | G3: =D3*1.1 -> 386100 | H3: =E3*1.1 -> 386100 | I3: =F3*1.1 -> 424710 | J3: =G3*1.1 -> 424710 | K3: =H3*1.1 -> 424710 | L3: =I3*1.1 -> 467181 | M3: =J3*1.1 -> 467181 | N3: =K3*1.1 -> 467181 | O3: =SUM(C3:N3) -> 4886973
B4: CUG Subscription | N4: =300000*1.3 -> 390000 | O4: =SUM(C4:N4) -> 390000
B5: Office Internet | D5: =645000+(645000*0.3) -> 838500 | G5: =D5 -> 838500 | J5: =G5*1.2 -> 1006200 | M5: =J5 -> 1006200 | O5: =SUM(C5:N5) -> 3689400
B6: Total | C6: =SUM(C3:C5) -> 351000 | D6: =SUM(D3:D5) -> 1189500 | E6: =SUM(E3:E5) -> 351000 | F6: =SUM(F3:F5) -> 386100 | G6: =SUM(G3:G5) -> 1224600 | H6: =SUM(H3:H5) -> 386100 | I6: =SUM(I3:I5) -> 424710 | J6: =SUM(J3:J5) -> 1430910 | ... O6: =SUM(O3:O5) -> 8966373
B8: Personnel Expenses
B9: Salaries and Allowance | C9: 6886501.5 | D9: 6886501.5 | E9: 6886501.5 | F9: 6886501.5 | G9: 6886501.5 | H9: 6886501.5 | I9: 6886501.5 | J9: 6886501.5 | K9: 6886501.5 | L9: 6886501.5 | M9: 6886501.5 | N9: 6886501.5 | O9: =SUM(C9:N9) -> 82638017
B10: Leave Allowance | E10: 150000 | F10: 685742 | H10: =300000+465134.06 -> 765134.06 | I10: 150000 | K10: =300000+597864 -> 897864 | L10: 382570.29 | M10: 150000 | N10: 298494.2 | O10: =SUM(C10:N10) -> 3479804.6
B11: Bonus | C11: =C9*0.75 -> 5164876.1 | I11: =G9*0.75 -> 5164876.1 | L11: =J9*0.75 -> 5164876.1 | O11: =SUM(C11:N11) -> 15494628
B12: 13th Month Salary | N12: =N9+N16 -> 9786916 | O12: =SUM(C12:N12) -> 9786916
B13: Promotion | I13: =C9*0.25 -> 1721625.4
B14: Staff end of the year package | N14: =1060000*1.3 -> 1378000 | O14: =SUM(C14:N14) -> 1378000
B15: Staff Training and development | E15: 2700000 | H15: 2700000 | K15: 2700000 | N15: 2700000 | O15: =SUM(C15:N15) -> 10800000
B16: New Staff Salary | C16: 2900414.6 | D16: 2900414.6 | E16: 2900414.6 | F16: 2900414.6 | G16: 2900414.6 | H16: 2900414.6 | I16: 2900414.6 | J16: 2900414.6 | K16: 2900414.6 | L16: 2900414.6 | M16: 2900414.6 | N16: 2900414.6 | O16: =SUM(C16:N16) -> 34804975
B17: Bonus for new staff | I17: =I16*0.75 -> 2175310.9 | N17: =N16*0.75 -> 2175310.9 | O17: =SUM(C17:N17) -> 4350621.8
B18: Long service award | L18: 5500000 | O18: =SUM(C18:N18) -> 5500000
B19: Employer's Pension | C19: 497114.94 | D19: 497114.94 | E19: 497114.94 | F19: 497114.94 | G19: 497114.94 | H19: 497114.94 | I19: 497114.94 | J19: 497114.94 | K19: 497114.94 | L19: 497114.94 | M19: 497114.94 | N19: 497114.94 | O19: =SUM(C19:N19) -> 5965379.2
B20: Employer's Pension (New Staff) | C20: 113399.46 | D20: 113399.46 | E20: 113399.46 | F20: 113399.46 | G20: 113399.46 | H20: 113399.46 | I20: 113399.46 | J20: 113399.46 | K20: 113399.46 | L20: 113399.46 | M20: 113399.46 | N20: 113399.46 | O20: =SUM(C20:N20) -> 1360793.5
B21: NSITF Regularization | E21: 2761297 | O21: =SUM(C21:N21) -> 2761297
B22: NSITF | E22: =N12*12 *0.01 -> 1174429.9 | O22: =SUM(C22:N22) -> 1174429.9
B23: ITF | L23: =N12*12 *0.01 -> 1174429.9 | O23: =SUM(C23:N23) -> 1174429.9
B24: Pre employment Medicals | C24: =144000+(144000*0.3) -> 187200 | O24: =SUM(C24:N24) -> 187200
B25: Onboarding | C25: =35700+(35700*0.3) -> 46410 | O25: =SUM(C25:N25) -> 46410
B26: Contigency | N26: 3000000 | O26: =SUM(C26:N26) -> 3000000
B27: Total | C27: =SUM(C9:C25) -> 15795917 | D27: =SUM(D9:D25) -> 10397430 | E27: =SUM(E9:E25) -> 17183157 | F27: =SUM(F9:F25) -> 11083172 | G27: =SUM(G9:G25) -> 10397430 | H27: =SUM(H9:H25) -> 13862564 | I27: =SUM(I9:I25) -> 19609243 | J27: =SUM(J9:J25) -> 10397430 | ... N27: =SUM(N9:N25) -> 26736152 | O27: =SUM(O9:O26) -> 1.839029e+08
B29: Insurance
B30: Hmo | H30: =6762362+(6762362*0.3) -> 8791070.6 | O30: =SUM(C30:N30) -> 8791070.6
B31: Group Life | L31: =2223817.27+(2223817.27*0.3) -> 2890962.5 | O31: =SUM(C31:N31) -> 2890962.5
B32: Fire & Buglary | G32: =271823*1.3 -> 353369.9 | O32: =SUM(C32:N32) -> 353369.9
B33: Vehicle | D33: =110000*1.3 -> 143000 | N33: =351000*1.3 -> 456300 | O33: =SUM(C33:N33) -> 599300
B34: Total | C34: =SUM(C30:C33) -> 0 | D34: =SUM(D30:D33) -> 143000 | E34: =SUM(E30:E33) -> 0 | F34: =SUM(F30:F33) -> 0 | G34: =SUM(G30:G33) -> 353369.9 | H34: =SUM(H30:H33) -> 8791070.6 | I34: =SUM(I30:I33) -> 0 | J34: =SUM(J30:J33) -> 0 | ... O34: =SUM(O30:O33) -> 12634703
B37: Sport and Fitness
B38: Field usage and aerobics | C38: =380000*1.3 -> 494000 | D38: =380000*1.3 -> 494000 | E38: =380000*1.3 -> 494000 | F38: =C38*1.1 -> 543400 | G38: =D38*1.1 -> 543400 | H38: =E38*1.1 -> 543400 | I38: =F38*1.1 -> 597740 | J38: =G38*1.1 -> 597740 | K38: =H38*1.1 -> 597740 | L38: =I38*1.1 -> 657514 | M38: =J38*1.1 -> 657514 | N38: =K38*1.1 -> 657514 | O38: =SUM(C38:N38) -> 6877962
B39: Entertainment | C39: =109240*1.3 -> 142012 | D39: =109240*1.3 -> 142012 | E39: =109240*1.3 -> 142012 | F39: 131008 | G39: 131008 | H39: 131008 | I39: 131008 | J39: 131008 | K39: 131008 | L39: 131008 | M39: 131008 | N39: 131008 | O39: =SUM(C39:N39) -> 1605108
B40: Players Logistics | C40: 200000 | D40: 200000 | E40: 200000 | F40: 200000 | G40: 200000 | H40: 200000 | I40: 200000 | J40: 200000 | K40: 200000 | L40: 200000 | M40: 200000 | N40: 200000 | O40: =SUM(C40:N40) -> 2400000
B41: Total | C41: =SUM(C38:C40) -> 836012 | D41: =SUM(D38:D40) -> 836012 | E41: =SUM(E38:E40) -> 836012 | F41: =SUM(F38:F40) -> 874408 | G41: =SUM(G38:G40) -> 874408 | H41: =SUM(H38:H40) -> 874408 | I41: =SUM(I38:I40) -> 928748 | J41: =SUM(J38:J40) -> 928748 | ... O41: =SUM(O38:O40) -> 10883070
G43: =SUM(F38:K38) -> 3423420
B44: Repairs and Maintenance
B45: Vehicle Repairs | C45: =50000*1.3 -> 65000 | D45: =50000*1.3 -> 65000 | E45: =50000*1.3 -> 65000 | F45: =C45*1.1 -> 71500 | G45: =D45*1.1 -> 71500 | H45: =E45*1.1 -> 71500 | I45: =F45*1.1 -> 78650 | J45: =G45*1.1 -> 78650 | K45: =H45*1.1 -> 78650 | L45: 50000 | M45: 50000 | N45: 50000 | O45: =SUM(C45:N45) -> 795450
B46: Motor vehicle renewal | D46: =25000*1.3 -> 32500 | N46: 25000 | O46: =SUM(C46:N46) -> 57500
B47: Vehicle Maintenance | E47: =107200*1.3 -> 139360 | H47: 107200 | K47: 107200 | N47: 107200 | O47: =SUM(C47:N47) -> 460960
B48: Total | C48: =SUM(C45:C47) -> 65000 | D48: =SUM(D45:D47) -> 97500 | E48: =SUM(E45:E47) -> 204360 | F48: =SUM(F45:F47) -> 71500 | G48: =SUM(G45:G47) -> 71500 | H48: =SUM(H45:H47) -> 178700 | I48: =SUM(I45:I47) -> 78650 | J48: =SUM(J45:J47) -> 78650 | ... O48: =SUM(O45:O47) -> 1313910
B51: Rent Related
B52: Annual Rent | G52: =26460000*1.3 -> 34398000 | O52: =SUM(C52:N52) -> 34398000
B53: Sevice charges (annually) | G53: 1222837.1 | O53: =SUM(C53:N53) -> 1222837.1
B54: Electricity supply charges (Quarterly ) | C54: =1293521.1*1.2 -> 1552225.3 | F54: =C54*1.1 -> 1707447.9 | I54: =F54*1.1 -> 1878192.6 | L54: =I54*1.1 -> 2066011.9 | O54: =SUM(C54:N54) -> 7203877.7
B55: Total | C55: =SUM(C52:C53) -> 0 | D55: =SUM(D52:D53) -> 0 | E55: =SUM(E52:E53) -> 0 | F55: =SUM(F52:F53) -> 0 | G55: =SUM(G52:G53) -> 35620837 | H55: =SUM(H52:H53) -> 0 | I55: =SUM(I52:I53) -> 0 | J55: =SUM(J52:J53) -> 0 | ... N55: =SUM(N52:N53) -> 0 | O55: =SUM(O52:O54) -> 42824715
B58: Birthday Gift
B59: Staff Gift | C59: 40000 | D59: 20000 | E59: 100000 | F59: 20000 | G59: 60000 | H59: 20000 | I59: 20000 | J59: 60000 | K59: 20000 | L59: 20000 | M59: 20000 | N59: 80000 | O59: =SUM(C59:N59) -> 480000
B60: Total | C60: =SUM(C58:C59) -> 40000 | D60: =SUM(D59:D59) -> 20000 | E60: =SUM(E59:E59) -> 100000 | F60: =SUM(F59:F59) -> 20000 | G60: =SUM(G59:G59) -> 60000 | H60: =SUM(H59:H59) -> 20000 | I60: =SUM(I59:I59) -> 20000 | J60: =SUM(J59:J59) -> 60000 | K60: =SUM(K59:K59) -> 20000 | ... O60: =SUM(O59:O59) -> 480000
B62: Fuelling
B63: Pool Car | C63: =80000+ (80000*0.3) -> 104000 | D63: =80000+ (80000*0.3) -> 104000 | E63: =80000+ (80000*0.3) -> 104000 | F63: =C63*1.1 -> 114400 | G63: =D63*1.1 -> 114400 | H63: =E63*1.1 -> 114400 | I63: =F63*1.1 -> 125840 | J63: =G63*1.1 -> 125840 | K63: =H63*1.1 -> 125840 | L63: =I63*1.1 -> 138424 | M63: =J63*1.1 -> 138424 | N63: =K63*1.1 -> 138424 | O63: =SUM(C63:N63) -> 1447992
B64: MD's Car | C64: =80000+ (80000*0.3) -> 104000 | D64: =80000+ (80000*0.3) -> 104000 | E64: =80000+ (80000*0.3) -> 104000 | F64: =C64*1.1 -> 114400 | G64: =D64*1.1 -> 114400 | H64: =E64*1.1 -> 114400 | I64: =F64*1.1 -> 125840 | J64: =G64*1.1 -> 125840 | K64: =H64*1.1 -> 125840 | L64: =I64*1.1 -> 138424 | M64: =J64*1.1 -> 138424 | N64: =K64*1.1 -> 138424 | O64: =SUM(C64:N64) -> 1447992
B65: BM's Car | C65: =60000+ (30000*0.3) -> 69000 | D65: =60000+ (30000*0.3) -> 69000 | E65: =60000+ (30000*0.3) -> 69000 | F65: =C65*1.1 -> 75900 | G65: =D65*1.1 -> 75900 | H65: =E65*1.1 -> 75900 | I65: =F65*1.1 -> 83490 | J65: =G65*1.1 -> 83490 | K65: =H65*1.1 -> 83490 | L65: =I65*1.1 -> 91839 | M65: =J65*1.1 -> 91839 | N65: =K65*1.1 -> 91839 | O65: =SUM(C65:N65) -> 960687
B66: Total | C66: =SUM(C63:C65) -> 277000 | D66: =SUM(D63:D65) -> 277000 | E66: =SUM(E63:E65) -> 277000 | F66: =SUM(F63:F65) -> 304700 | G66: =SUM(G63:G65) -> 304700 | H66: =SUM(H63:H65) -> 304700 | I66: =SUM(I63:I65) -> 335170 | J66: =SUM(J63:J65) -> 335170 | ... O66: =SUM(O63:O65) -> 3856671
B68: Team Bonding
B69: Weekly Lunch | C69: =81000*4 -> 324000 | D69: =81000*4 -> 324000 | E69: =81000*4 -> 324000 | F69: =81000*4 -> 324000 | G69: =81000*4 -> 324000 | H69: =81000*4 -> 324000 | I69: =81000*4 -> 324000 | J69: =81000*4 -> 324000 | ... N69: =81000*4 -> 324000 | O69: =SUM(C69:N69) -> 3888000
B70: Quarterly Team Bonding | E70: 725000 | H70: 725000 | K70: 725000 | O70: =SUM(C70:N70) -> 2175000
B71: Total | C71: =SUM(C69:C70) -> 324000 | D71: =SUM(D69:D70) -> 324000 | E71: =SUM(E69:E70) -> 1049000 | F71: =SUM(F69:F70) -> 324000 | G71: =SUM(G69:G70) -> 324000 | H71: =SUM(H69:H70) -> 1049000 | I71: =SUM(I69:I70) -> 324000 | J71: =SUM(J69:J70) -> 324000 | ... O71: =SUM(O69:O70) -> 6063000
B73: General Office Expense
B74: Stationery | D74: =40000+(40000*0.3) -> 52000 | F74: =D74*1.1 -> 57200 | H74: =F74*1.1 -> 62920 | J74: =H74*1.1 -> 69212 | L74: =J74*1.1 -> 76133.2 | N74: =L74*1.1 -> 83746.52 | O74: =SUM(C74:N74) -> 401211.72
B75: Printables (Letter head, deal slips, requisitions) | C75: =62500+35000 -> 97500 | E75: =170000+120000 -> 290000 | I75: 75000 | O75: =SUM(C75:N75) -> 462500
B76: Office supplies and Provisions | C76: =312000+(312000*0.3) -> 405600 | D76: =312000+(312000*0.3) -> 405600 | E76: =312000+(312000*0.3) -> 405600 | F76: =C76*1.1 -> 446160 | G76: =D76*1.1 -> 446160 | H76: =E76*1.1 -> 446160 | I76: =F76*1.1 -> 490776 | J76: =G76*1.1 -> 490776 | K76: =H76*1.1 -> 490776 | L76: =I76*1.1 -> 539853.6 | M76: =J76*1.1 -> 539853.6 | N76: =K76*1.1 -> 539853.6 | O76: =SUM(C76:N76) -> 5647168.8
B77: Total | C77: =SUM(C74:C76) -> 503100 | D77: =SUM(D74:D76) -> 457600 | E77: =SUM(E74:E76) -> 695600 | F77: =SUM(F74:F76) -> 503360 | G77: =SUM(G74:G76) -> 446160 | H77: =SUM(H74:H76) -> 509080 | I77: =SUM(I74:I76) -> 565776 | J77: =SUM(J74:J76) -> 559988 | ... O77: =SUM(O74:O76) -> 6510880.5
B79: Training and Team Building
B80: Strategy Retreat | H80: 5000000 | O80: =SUM(C80:N80) -> 5000000
B81: Total | C81: =SUM(C80:C80) -> 0 | D81: =SUM(D80:D80) -> 0 | E81: =SUM(E80:E80) -> 0 | F81: =SUM(F80:F80) -> 0 | G81: =SUM(G80:G80) -> 0 | H81: =SUM(H80:H80) -> 5000000 | I81: =SUM(I80:I80) -> 0 | J81: =SUM(J80:J80) -> 0 | ... O81: =SUM(O80:O80) -> 5000000
B83: Staff Event
B84: Staff end of the year Party | N84: =5000000*1.5 -> 7500000 | O84: =SUM(C84:N84) -> 7500000
B85: Total | C85: =SUM(C84:C84) -> 0 | D85: =SUM(D84:D84) -> 0 | E85: =SUM(E84:E84) -> 0 | F85: =SUM(F84:F84) -> 0 | G85: =SUM(G84:G84) -> 0 | H85: =SUM(H84:H84) -> 0 | I85: =SUM(I84:I84) -> 0 | J85: =SUM(J84:J84) -> 0 | ... M85: =SUM(M84:M84) -> 0 | N85: =5000000*1.5 -> 7500000 | O85: =SUM(O84:O84) -> 7500000
O86: =SUM(C86:N86) -> 0
B87: Funmigation | C87: 300000 | N87: =C87*1.3 -> 390000
B89: Travelling Expenses | O89: =SUM(C89:N89) -> 0
B90: Flight Ticket | C90: 650000 | D90: 650000 | E90: 650000 | F90: =C90*1.1 -> 715000 | G90: =D90*1.1 -> 715000 | H90: =E90*1.1 -> 715000 | I90: =F90*1.1 -> 786500 | J90: =G90*1.1 -> 786500 | K90: =H90*1.1 -> 786500 | L90: =I90*1.1 -> 865150 | M90: 650000 | N90: 650000 | O90: =SUM(C90:N90) -> 8619650
B91: Hotel and Reservations | C91: =62500/0.3 -> 208333.33 | D91: =62500/0.3 -> 208333.33 | E91: =62500/0.3 -> 208333.33 | F91: =C91*1.1 -> 229166.67 | G91: =D91*1.1 -> 229166.67 | H91: =E91*1.1 -> 229166.67 | I91: =F91*1.1 -> 252083.33 | J91: =G91*1.1 -> 252083.33 | K91: =H91*1.1 -> 252083.33 | L91: =I91*1.1 -> 277291.67 | M91: =J91*1.1 -> 277291.67 | N91: =K91*1.1 -> 277291.67 | O91: =SUM(C91:N91) -> 2900625
B92: Logistics | C92: =25000/0.3 -> 83333.333 | D92: =25000/0.3 -> 83333.333 | E92: =25000/0.3 -> 83333.333 | F92: =25000/0.3 -> 83333.333 | G92: =25000/0.3 -> 83333.333 | H92: =25000/0.3 -> 83333.333 | I92: =25000/0.3 -> 83333.333 | J92: =25000/0.3 -> 83333.333 | ... N92: =25000/0.3 -> 83333.333 | O92: =SUM(C92:N92) -> 1000000
B93: Feeding | C93: =30000/0.3 -> 100000 | D93: =30000/0.3 -> 100000 | E93: =30000/0.3 -> 100000 | F93: =30000/0.3 -> 100000 | G93: =30000/0.3 -> 100000 | H93: =30000/0.3 -> 100000 | I93: =30000/0.3 -> 100000 | J93: =30000/0.3 -> 100000 | ... N93: =30000/0.3 -> 100000 | O93: =SUM(C93:N93) -> 1200000
B94: Total | C94: =SUM(C90:C93) -> 1041666.7 | D94: =SUM(D90:D93) -> 1041666.7 | E94: =SUM(E90:E93) -> 1041666.7 | F94: =SUM(F90:F93) -> 1127500 | G94: =SUM(G90:G93) -> 1127500 | H94: =SUM(H90:H93) -> 1127500 | I94: =SUM(I90:I93) -> 1221916.7 | J94: =SUM(J90:J93) -> 1221916.7 | ... N94: =SUM(N90:N93) -> 1110625

Sheet HR AND ADMIN BUDGET
B2: SohCahToa Holdings Departmental Template
B3: HR and Admin Budget
B4: Expense Heads | C4: January | D4: February | E4: March | F4: April | G4: May | H4: June | I4: July | J4: August | K4: September | L4: October | M4: November | N4: December | O4: Total
B5: Rent | C5: ='Input Worksheet'!C49 -> 0 | D5: ='Input Worksheet'!D49 -> 0 | E5: ='Input Worksheet'!E49 -> 34900000 | F5: ='Input Worksheet'!F49 -> 0 | G5: ='Input Worksheet'!G49 -> 0 | H5: ='Input Worksheet'!H49 -> 21861657 | I5: ='Input Worksheet'!I49 -> 0 | J5: ='Input Worksheet'!J49 -> 0 | ... N5: ='Input Worksheet'!N49 -> 4492800 | O5: =SUM(C5:N5) -> 64710457
B6: Birthday Gifts | C6: ='Input Worksheet'!C54 -> 40000 | D6: ='Input Worksheet'!D54 -> 40000 | E6: ='Input Worksheet'!E54 -> 240000 | F6: ='Input Worksheet'!F54 -> 40000 | G6: ='Input Worksheet'!G54 -> 80000 | H6: ='Input Worksheet'!H54 -> 80000 | I6: ='Input Worksheet'!I54 -> 80000 | J6: ='Input Worksheet'!J54 -> 280000 | ... N6: ='Input Worksheet'!N54 -> 80000 | O6: =SUM(C6:N6) -> 1880000
B7: Insurance | C7: ='Input Worksheet'!C28 -> 7042958.1 | D7: ='Input Worksheet'!D28 -> 5146814.6 | E7: ='Input Worksheet'!E28 -> 3355941.4 | F7: ='Input Worksheet'!F28 -> 3853173.4 | G7: ='Input Worksheet'!G28 -> 843380.87 | H7: ='Input Worksheet'!H28 -> 8073232 | I7: ='Input Worksheet'!I28 -> 4177173.4 | J7: ='Input Worksheet'!J28 -> 0 | ... N7: ='Input Worksheet'!N28 -> 8600000 | O7: =SUM(C7:N7) -> 49440764
B8: Repairs and Maintenance | C8: ='Input Worksheet'!C42 -> 405000 | D8: ='Input Worksheet'!D42 -> 300000 | E8: ='Input Worksheet'!E42 -> 621000 | F8: ='Input Worksheet'!F42 -> 500000 | G8: ='Input Worksheet'!G42 -> 500000 | H8: ='Input Worksheet'!H42 -> 800000 | I8: ='Input Worksheet'!I42 -> 500000 | J8: ='Input Worksheet'!J42 -> 542000 | ... N8: ='Input Worksheet'!N42 -> 1750000 | O8: =SUM(C8:N8) -> 8481000
B9: Fuelling | C9: ='Input Worksheet'!C61 -> 2800000 | D9: ='Input Worksheet'!D61 -> 3000000 | E9: ='Input Worksheet'!E61 -> 3070000 | F9: ='Input Worksheet'!F61 -> 3499600 | G9: ='Input Worksheet'!G61 -> 3499600 | H9: ='Input Worksheet'!H61 -> 3569600 | I9: ='Input Worksheet'!I61 -> 4124000.1 | J9: ='Input Worksheet'!J61 -> 4904375.3 | ... N9: ='Input Worksheet'!N61 -> 7168634.4 | O9: =SUM(C9:N9) -> 55782767
B10: Travelling Expense | C10: ='Input Worksheet'!C92 -> 7000000 | H10: ='Input Worksheet'!H92 -> 16600000 | M10: ='Input Worksheet'!M92 -> 47800000 | O10: =SUM(C10:N10) -> 71400000
B11: Team Bonding | C11: ='Input Worksheet'!C66 -> 897000 | D11: ='Input Worksheet'!D66 -> 975000 | E11: ='Input Worksheet'!E66 -> 2757000 | F11: ='Input Worksheet'!F66 -> 1209000 | G11: ='Input Worksheet'!G66 -> 1209000 | H11: ='Input Worksheet'!H66 -> 3054000 | I11: ='Input Worksheet'!I66 -> 1326000 | J11: ='Input Worksheet'!J66 -> 1326000 | ... N11: ='Input Worksheet'!N66 -> 1326000 | O11: =SUM(C11:N11) -> 20037000
B12: General office Expenses | C12: ='Input Worksheet'!C72 -> 603417.62 | D12: ='Input Worksheet'!D72 -> 588432 | E12: ='Input Worksheet'!E72 -> 1465052.3 | F12: ='Input Worksheet'!F72 -> 953259.84 | G12: ='Input Worksheet'!G72 -> 1211388.8 | H12: ='Input Worksheet'!H72 -> 1348444.4 | I12: ='Input Worksheet'!I72 -> 1480432.7 | J12: ='Input Worksheet'!J72 -> 1268788.8 | ... N12: ='Input Worksheet'!N72 -> 1522288.8 | O12: =SUM(C12:N12) -> 15060112
B13: Training and Team building | C13: ='Input Worksheet'!C76 -> 30000000 | D13: ='Input Worksheet'!D76 -> 0 | E13: ='Input Worksheet'!E76 -> 0 | F13: ='Input Worksheet'!F76 -> 0 | G13: ='Input Worksheet'!G76 -> 0 | H13: ='Input Worksheet'!H76 -> 0 | I13: ='Input Worksheet'!I76 -> 0 | J13: ='Input Worksheet'!J76 -> 0 | ... N13: ='Input Worksheet'!N76 -> 0 | O13: =SUM(C13:N13) -> 30000000
B14: Funmigation & Consultants | C14: ='Input Worksheet'!C86 -> 450000 | D14: ='Input Worksheet'!D86 -> 0 | E14: ='Input Worksheet'!E86 -> 5000000 | F14: ='Input Worksheet'!F86 -> 0 | G14: ='Input Worksheet'!G86 -> 0 | H14: ='Input Worksheet'!H86 -> 5580500 | I14: ='Input Worksheet'!I86 -> 0 | J14: ='Input Worksheet'!J86 -> 0 | ... N14: ='Input Worksheet'!N86 -> 0
B15: Staff Events | C15: ='Input Worksheet'!C81 -> 0 | D15: ='Input Worksheet'!D81 -> 0 | E15: ='Input Worksheet'!E81 -> 0 | F15: ='Input Worksheet'!F81 -> 0 | G15: ='Input Worksheet'!G81 -> 0 | H15: ='Input Worksheet'!H81 -> 0 | I15: ='Input Worksheet'!I81 -> 0 | J15: ='Input Worksheet'!J81 -> 0 | ... N15: ='Input Worksheet'!N81 -> 25800000 | O15: =SUM(C15:N15) -> 29919615
B16: Sports and Fitness | C16: ='Input Worksheet'!C35 -> 2365333.3 | D16: ='Input Worksheet'!D35 -> 2311333.3 | E16: ='Input Worksheet'!E35 -> 2661333.3 | F16: ='Input Worksheet'!F35 -> 3287086 | G16: ='Input Worksheet'!G35 -> 3179086 | H16: ='Input Worksheet'!H35 -> 3179086 | I16: ='Input Worksheet'!I35 -> 3413006.6 | J16: ='Input Worksheet'!J35 -> 3305006.6 | ... N16: ='Input Worksheet'!N35 -> 3462382.3 | O16: =SUM(C16:N16) -> 37393425
B17: Personnel Cost | C17: ='Input Worksheet'!C21 -> 13641222 | D17: ='Input Worksheet'!D21 -> 16237204 | E17: ='Input Worksheet'!E21 -> 27949214 | F17: ='Input Worksheet'!F21 -> 26994693 | G17: ='Input Worksheet'!G21 -> 18287995 | H17: ='Input Worksheet'!H21 -> 32768566 | I17: ='Input Worksheet'!I21 -> 38459526 | J17: ='Input Worksheet'!J21 -> 20303065 | ... N17: ='Input Worksheet'!N21 -> 64597783 | O17: =SUM(C17:N17) -> 3.5050137e+08
B18: Capital Expenditure | C18: 172000000 | D18: ='Capital Expenditure'!D9 -> 0 | F18: ='Capital Expenditure'!F9 -> 0 | G18: ='Capital Expenditure'!G9 -> 0 | H18: ='Capital Expenditure'!H9 -> 0 | I18: ='Capital Expenditure'!I9 -> 0 | J18: ='Capital Expenditure'!J9 -> 0 | K18: ='Capital Expenditure'!K9 -> 0 | L18: ='Capital Expenditure'!L9 -> 0 | M18: ='Capital Expenditure'!M9 -> 0 | N18: ='Capital Expenditure'!N9 -> 0 | O18: =SUM(C18:N18) -> 172000000
B19: Total | C19: =SUM(C5:C18) -> 2.3724493e+08 | D19: =SUM(D5:D18) -> 28598784 | E19: =SUM(E5:E18) -> 82019541 | F19: =SUM(F5:F18) -> 40336813 | G19: =SUM(G5:G18) -> 28810451 | H19: =SUM(H5:H18) -> 96915085 | I19: =SUM(I5:I18) -> 53560139 | J19: =SUM(J5:J18) -> 31929236 | ... O19: =SUM(O5:O18) -> 9.0660651e+08

Sheet Input Worksheet
C1: January | D1: February | E1: March | F1: April | G1: May | H1: June | I1: July | J1: August | K1: September | L1: October | M1: November | N1: December | O1: Total
B3: Personnel Expenses
B4: Salaries and Allowance | C4: 9789866.7 | D4: =SUM(C4,C11) -> 11688368 | E4: =SUM(D4,D11) -> 12118543 | F4: =SUM(E4,E11) -> 13384543 | G4: =SUM(F4,F11) -> 15686543 | H4: =SUM(G4,G11) -> 15686543 | I4: =SUM(H4,H11) -> 15686543 | J4: =SUM(I4,I11) -> 17186543 | K4: =SUM(J4,J11) -> 17186543 | ... N4: =SUM(M4,M11) -> 17186543 | O4: =SUM(C4:N4) -> 1.7997367e+08
B5: Leave Allowance | E5: 145663.79 | F5: 279, 185.316 | G5: 111793.5 | H5: =60047.352+182317.2 -> 242364.55 | I5: =70724.748+111793.5 -> 182518.25 | J5: =180600+180600+ 145663.79 -> 506863.79 | K5: =279185.316 +126114.68 +111793.5+378000 -> 895093.5 | L5: =174075.444 +174075.444+152917.2 -> 501068.09 | M5: =111793.5 +111793.5 -> 223587 | N5: =111793.5 +111793.5 -> 223587 | O5: =SUM(C5:N5) -> 3032539.5
B6: Bonus | F6: 8656342 | I6: 9789867 | L6: =SUM(C4,242000,242000,D11,E11) -> 11970042 | O6: =SUM(C6:N6) -> 30416251
B7: 13th Month Salary | N7: =N4 -> 17186543 | O7: =SUM(C7:N7) -> 17186543
B8: Promotion | I8: =(14742806.36-C4)+3000000 -> 7952939.7 | O8: =SUM(C8:N8) -> 7952939.7
B9: Staff end of the year package | N9: =0.2498*3993800+(3993800) -> 4991451.2 | O9: =SUM(C9:N9) -> 4991451.2
B10: Staff Training and development | E10: =400000*30 -> 12000000 | H10: =400000*33+1100000 -> 14300000 | I10: 575850 | K10: =400000*36 -> 14400000 | L10: 1025000 | M10: 985000 | N10: =400000*36 -> 14400000 | O10: =SUM(C10:N10) -> 57685850
B11: New Staff Salary | C11: =955987.17+ 942514.55 -> 1898501.7 | D11: =255175+175000 -> 430175 | E11: =422000+422000+422000 -> 1266000 | F11: =1200000+680000+422000 -> 2302000 | I11: =500000+500000+500000 -> 1500000 | O11: =SUM(C11:N11) -> 7396676.7
B12: Long service award | C12: =50000*2 -> 100000 | H12: 50000 | O12: =SUM(C12:N12) -> 150000
B13: Drivers' Salary | C13: 798454 | D13: 1136857 | E13: 1136857 | F13: =1136857+112801 -> 1249658 | G13: =1136857+112801 -> 1249658 | H13: =1136857+112801 -> 1249658 | I13: =1136857+112801 -> 1249658 | J13: =1136857+112801 -> 1249658 | K13: =1136857+112801 -> 1249658 | L13: =1136857+112801 -> 1249658 | M13: =1136857+112801 -> 1249658 | N13: =1136857+112801 -> 1249658 | O13: =SUM(C13:N13) -> 14319090
B14: NSITF Regularization | D14: =(O4+O11)*0.01 -> 1873703.5 | O14: =SUM(C14:N14) -> 1873703.5
B15: NSITF | O15: =SUM(C15:N15) -> 0
B16: ITF | L16: =(O4+O11)*0.01 -> 1873703.5 | O16: =SUM(C16:N16) -> 1873703.5
B17: Pre employment Medicals | C17: =44800*3 -> 134400 | D17: =44800*2 -> 89600 | E17: =44800*3 -> 134400 | F17: =44800*3 -> 134400 | I17: =F17 -> 134400 | O17: =SUM(C17:N17) -> 627200
B18: Onboarding | D18: =(4750+4500)*2 -> 18500 | E18: =(4750+4500)*3 -> 27750 | F18: =(4750+4500)*3 -> 27750 | I18: =F18 -> 27750 | J18: =$H18+0.03*$H18 -> 0 | K18: =$H18+0.03*$H18 -> 0 | L18: =$K18+0.02*$K18 -> 0 | M18: =$K18+0.02*$K18 -> 0 | N18: =$K18+0.02*$K18 -> 0 | O18: =SUM(C18:N18) -> 101750
B19: Contigency (Staff exit) | N19: 8000000 | O19: =SUM(C19:N19) -> 8000000
B20: Transportation Allowance | C20: =40000*23 -> 920000 | D20: =40000*25 -> 1000000 | E20: =40000*28 -> 1120000 | F20: =40000*31 -> 1240000 | G20: =40000*31 -> 1240000 | H20: =40000*31 -> 1240000 | I20: =40000*34 -> 1360000 | J20: =40000*34 -> 1360000 | K20: =40000*34 -> 1360000 | L20: =40000*34 -> 1360000 | M20: =40000*34 -> 1360000 | N20: =40000*34 -> 1360000 | O20: =SUM(C20:N20) -> 14920000
B21: Total | C21: =SUM(C4:C20) -> 13641222 | D21: =SUM(D4:D20) -> 16237204 | E21: =SUM(E4:E20) -> 27949214 | F21: =SUM(F4:F20) -> 26994693 | G21: =SUM(G4:G20) -> 18287995 | H21: =SUM(H4:H20) -> 32768566 | I21: =SUM(I4:I20) -> 38459526 | J21: =SUM(J4:J20) -> 20303065 | ... O21: =SUM(O4:O20) -> 3.5050137e+08
B23: Insurance
B24: Hmo | C24: =201556+251945.5+99873+99873 -> 653247.5 | D24: =(99873*3)*2 -> 599238 | E24: =(99873*3)*3 -> 898857 | F24: =(99873*3)*3 -> 898857 | H24: 7873232 | I24: =F24 -> 898857 | O24: =SUM(C24:N24) -> 11822288
B25: Group Life | C25: 2090710.6 | D25: 2183628.4 | E25: 2457084.4 | F25: 2954316.4 | I25: 3278316.4 | L25: =30/100*5613915.405+5613915.405 -> 7298090 | O25: =SUM(C25:N25) -> 20262146
B26: Fire & Buglary | G26: =30/100*353369.9+353369.9 -> 459380.87 | O26: =SUM(C26:N26) -> 459380.87
B27: Vehicle | C27: =1000000+3299000 -> 4299000 | D27: 2363948.2 | G27: 384000 | H27: 200000 | L27: 400000 | M27: 650000 | N27: =2850000+5750000 -> 8600000 | O27: =SUM(C27:N27) -> 16896948
B28: Total | C28: =SUM(C24:C27) -> 7042958.1 | D28: =SUM(D24:D27) -> 5146814.6 | E28: =SUM(E24:E27) -> 3355941.4 | F28: =SUM(F24:F27) -> 3853173.4 | G28: =SUM(G24:G27) -> 843380.87 | H28: =SUM(H24:H27) -> 8073232 | I28: =SUM(I24:I27) -> 4177173.4 | J28: =SUM(J24:J27) -> 0 | ... O28: =SUM(O24:O27) -> 49440764
B31: Sport and Fitness
B32: Field usage and aerobics | C32: =303333.3+100000 -> 403333.3 | D32: =303333.3+100000 -> 403333.3 | E32: =303333.3+100000 -> 403333.3 | F32: =$E32*(24.98/100)+$E32 -> 504085.96 | G32: =$E32*(24.98/100)+$E32 -> 504085.96 | H32: =$E32*(24.98/100)+$E32 -> 504085.96 | I32: =$H32*(24.98/100)+$H32 -> 630006.63 | J32: =$H32*(24.98/100)+$H32 -> 630006.63 | K32: =$H32*(24.98/100)+$H32 -> 630006.63 | L32: =$K32*(24.98/100)+$K32 -> 787382.29 | M32: =$K32*(24.98/100)+$K32 -> 787382.29 | N32: =$K32*(24.98/100)+$K32 -> 787382.29 | O32: =SUM(C32:N32) -> 6974424.5
B33: Entertainment | C33: =350000*4 -> 1400000 | D33: =350000*4 -> 1400000 | E33: =350000*5 -> 1750000 | F33: =$E33*1.3 -> 2275000 | G33: =$E33*1.3 -> 2275000 | H33: =$E33*1.3 -> 2275000 | I33: =$E33*1.3 -> 2275000 | J33: =$E33*1.3 -> 2275000 | K33: =$E33*1.3 -> 2275000 | L33: =$E33*1.3 -> 2275000 | M33: =$E33*1.3 -> 2275000 | N33: =$E33*1.3 -> 2275000 | O33: =SUM(C33:N33) -> 25025000
B34: Players Logistics | C34: =(100000*4)+162000 -> 562000 | D34: =(100000*4)+108000 -> 508000 | E34: =(100000*4)+108000 -> 508000 | F34: =(100000*4)+108000 -> 508000 | G34: =100000*4 -> 400000 | H34: =100000*4 -> 400000 | I34: =(100000*4)+108000 -> 508000 | J34: =100000*4 -> 400000 | K34: =100000*4 -> 400000 | L34: =100000*4 -> 400000 | M34: =100000*4 -> 400000 | N34: =100000*4 -> 400000 | O34: =SUM(C34:N34) -> 5394000
B35: Total | C35: =SUM(C32:C34) -> 2365333.3 | D35: =SUM(D32:D34) -> 2311333.3 | E35: =SUM(E32:E34) -> 2661333.3 | F35: =SUM(F32:F34) -> 3287086 | G35: =SUM(G32:G34) -> 3179086 | H35: =SUM(H32:H34) -> 3179086 | I35: =SUM(I32:I34) -> 3413006.6 | J35: =SUM(J32:J34) -> 3305006.6 | ... O35: =SUM(O32:O34) -> 37393425
B38: Repairs and Maintenance
B39: Vehicle Repairs | C39: 300000 | D39: 300000 | E39: 300000 | F39: 500000 | G39: 500000 | H39: 500000 | I39: 500000 | J39: 500000 | K39: 500000 | L39: 750000 | M39: 750000 | N39: 750000 | O39: =SUM(C39:N39) -> 6150000
B40: Motor vehicle renewal | C40: 105000 | E40: 21000 | J40: 42000 | L40: =16500+4500 -> 21000 | M40: 42000 | O40: =SUM(C40:N40) -> 231000
B41: Vehicle Maintenance | E41: 300000 | H41: 300000 | K41: 500000 | N41: 1000000 | O41: =SUM(C41:N41) -> 2100000
B42: Total | C42: =SUM(C38:C41) -> 405000 | D42: =SUM(D38:D41) -> 300000 | E42: =SUM(E38:E41) -> 621000 | F42: =SUM(F38:F41) -> 500000 | G42: =SUM(G38:G41) -> 500000 | H42: =SUM(H38:H41) -> 800000 | I42: =SUM(I38:I41) -> 500000 | J42: =SUM(J38:J41) -> 542000 | ... N42: =SUM(N38:N41) -> 1750000 | O42: =SUM(O39:O41) -> 8481000
B45: Rent Related
B46: Annual Rent | E46: 30000000 | H46: 17199000 | O46: =SUM(C46:N46) -> 47199000
B47: Sevice charges (annually) | E47: 2500000 | H47: 1782656.8 | O47: =SUM(C47:N47) -> 4282656.8
B48: Electricity supply charges (monthly ) | E48: =800000*3 -> 2400000 | H48: =E48*1.2 -> 2880000 | K48: =H48*1.2 -> 3456000 | N48: =K48*1.3 -> 4492800 | O48: =SUM(C48:N48) -> 13228800
B49: Total | C49: =SUM(C46:C48) -> 0 | D49: =SUM(D46:D48) -> 0 | E49: =SUM(E46:E48) -> 34900000 | F49: =SUM(F46:F48) -> 0 | G49: =SUM(G46:G48) -> 0 | H49: =SUM(H46:H48) -> 21861657 | I49: =SUM(I46:I48) -> 0 | J49: =SUM(J46:J48) -> 0 | ... O49: =SUM(O46:O48) -> 64710457
B52: Birthday Gift
B53: Staff Gift | C53: =40000*1 -> 40000 | D53: =40000*1 -> 40000 | E53: =40000*6 -> 240000 | F53: =40000*1 -> 40000 | G53: =40000*2 -> 80000 | H53: =40000*2 -> 80000 | I53: =40000*2 -> 80000 | J53: =(40000*2)+200000 -> 280000 | K53: =40000*10 -> 400000 | L53: =40000*3 -> 120000 | M53: =400000*1 -> 400000 | N53: =40000*2 -> 80000 | O53: =SUM(C53:N53) -> 1880000
B54: Total | C54: =SUM(C53) -> 40000 | D54: =SUM(D53) -> 40000 | E54: =SUM(E53) -> 240000 | F54: =SUM(F53) -> 40000 | G54: =SUM(G53) -> 80000 | H54: =SUM(H53) -> 80000 | I54: =SUM(I53) -> 80000 | J54: =SUM(J53) -> 280000 | ... N54: =SUM(N53) -> 80000 | O54: =SUM(O53:O53) -> 1880000
B56: Fuelling
B57: Pool Car | C57: 200000 | D57: 200000 | E57: =200000+(200000*0.35) -> 270000 | F57: 200000 | G57: 200000 | H57: =200000+(200000*0.35) -> 270000 | I57: 200000 | J57: 200000 | K57: =200000+(200000*0.35) -> 270000 | L57: 200000 | M57: 200000 | N57: =200000+(200000*0.35) -> 270000 | O57: =SUM(C57:N57) -> 2680000
B58: MD's Cars | C58: 2000000 | D58: 2000000 | E58: 2000000 | F58: =$E58*(24.98/100)+$E58 -> 2499600 | G58: =$E58*(24.98/100)+$E58 -> 2499600 | H58: =$E58*(24.98/100)+$E58 -> 2499600 | I58: =H58*(24.98/100)+H58 -> 3124000.1 | J58: =I58*(24.98/100)+I58 -> 3904375.3 | K58: =J58*(24.98/100)+J58 -> 4879688.2 | L58: =$K58*(24.98/100)+$K58 -> 6098634.4 | M58: =$K58*(24.98/100)+$K58 -> 6098634.4 | N58: =$K58*(24.98/100)+$K58 -> 6098634.4 | O58: =SUM(C58:N58) -> 43702767
B59: Official Car | C59: =(100000*4)+200000 -> 600000 | D59: =(100000*6)+200000 -> 800000 | E59: =(100000*6)+200000 -> 800000 | F59: =(100000*6)+200000 -> 800000 | G59: =(100000*6)+200000 -> 800000 | H59: =(100000*6)+200000 -> 800000 | I59: =(100000*6)+200000 -> 800000 | J59: =(100000*6)+200000 -> 800000 | K59: =(100000*6)+200000 -> 800000 | ... N59: =(100000*6)+200000 -> 800000 | O59: =SUM(I59:N59) -> 4800000
B60: Staff Bus | C60: 226000 | D60: 226000 | E60: 226000 | F60: =$E60+($E60*0.3) -> 293800 | G60: =$E60+($E60*0.3) -> 293800 | H60: =$E60+($E60*0.3) -> 293800 | I60: =$H60+($H60*0.3) -> 381940 | J60: =$H60+($H60*0.3) -> 381940 | K60: =$H60+($H60*0.3) -> 381940 | L60: =$K60+($K60*0.3) -> 496522 | M60: =$K60+($K60*0.3) -> 496522 | N60: =$K60+($K60*0.3) -> 496522 | O60: =SUM(C60:N60) -> 4194786
B61: Total | C61: =SUM(C57:C59) -> 2800000 | D61: =SUM(D57:D59) -> 3000000 | E61: =SUM(E57:E59) -> 3070000 | F61: =SUM(F57:F59) -> 3499600 | G61: =SUM(G57:G59) -> 3499600 | H61: =SUM(H57:H59) -> 3569600 | I61: =SUM(I57:I59) -> 4124000.1 | J61: =SUM(J57:J59) -> 4904375.3 | ... O61: =SUM(O57:O59) -> 51182767
B63: Team Bonding
B64: Weekly Lunch | C64: =39000*23 -> 897000 | D64: =39000*25 -> 975000 | E64: =39000*28 -> 1092000 | F64: =39000*31 -> 1209000 | G64: =39000*31 -> 1209000 | H64: =39000*31 -> 1209000 | I64: =39000*34 -> 1326000 | J64: =39000*34 -> 1326000 | K64: =39000*34 -> 1326000 | L64: =39000*34 -> 1326000 | M64: =39000*34 -> 1326000 | N64: =39000*34 -> 1326000 | O64: =SUM(C64:N64) -> 14547000
B65: Quarterly Team Bonding | E65: =45000*37 -> 1665000 | H65: =45000*41 -> 1845000 | K65: =45000*44 -> 1980000 | O65: =SUM(C65:N65) -> 5490000
B66: Total | C66: =SUM(C64:C65) -> 897000 | D66: =SUM(D64:D65) -> 975000 | E66: =SUM(E64:E65) -> 2757000 | F66: =SUM(F64:F65) -> 1209000 | G66: =SUM(G64:G65) -> 1209000 | H66: =SUM(H64:H65) -> 3054000 | I66: =SUM(I64:I65) -> 1326000 | J66: =SUM(J64:J65) -> 1326000 | ... O66: =SUM(O64:O65) -> 20037000
B68: General Office Expense
B69: Stationery | C69: =83746.52+(83746*0.35) -> 113057.62 | E69: =C69+(C69*0.2) -> 135669.14 | G69: =E69+(E69*0.2) -> 162802.97 | I69: =G69+(G69*0.3) -> 211643.86 | K69: =I69+(I69*0.2) -> 253972.64 | M69: =K69+(K69*0.2) -> 304767.17 | O69: =SUM(C69:N69) -> 1181913.4
B70: Printables (Letter head, deal slips, requisitions) | E70: =70000+50000+75000+340000 -> 535000 | H70: =70000+50000+75000 -> 195000 | K70: =H70*1.3 -> 253500 | N70: =K70 -> 253500 | O70: =SUM(C70:N70) -> 1237000
B71: Office supplies and Provisions | C71: 490360 | D71: =C71+(C71*0.2) -> 588432 | E71: =D71+(D71*0.35) -> 794383.2 | F71: =E71+(E71*0.2) -> 953259.84 | G71: =F71+(F71*0.1) -> 1048585.8 | H71: =G71+(G71*0.1) -> 1153444.4 | I71: =H71+(H71*0.1) -> 1268788.8 | J71: =I71 -> 1268788.8 | K71: =I71 -> 1268788.8 | L71: =I71 -> 1268788.8 | M71: =I71 -> 1268788.8 | N71: =I71 -> 1268788.8 | O71: =SUM(C71:N71) -> 12641198
B72: Total | C72: =SUM(C69:C71) -> 603417.62 | D72: =SUM(D69:D71) -> 588432 | E72: =SUM(E69:E71) -> 1465052.3 | F72: =SUM(F69:F71) -> 953259.84 | G72: =SUM(G69:G71) -> 1211388.8 | H72: =SUM(H69:H71) -> 1348444.4 | I72: =SUM(I69:I71) -> 1480432.7 | J72: =SUM(J69:J71) -> 1268788.8 | ... O72: =SUM(O69:O71) -> 15060112
B74: Training and Team Building
B75: Strategy Retreat | C75: 30000000 | O75: =SUM(C75:N75) -> 30000000
B76: Total | C76: =SUM(C75) -> 30000000 | D76: =SUM(D75) -> 0 | E76: =SUM(E75) -> 0 | F76: =SUM(F75) -> 0 | G76: =SUM(G75) -> 0 | H76: =SUM(H75) -> 0 | I76: =SUM(I75) -> 0 | J76: =SUM(J75) -> 0 | ... N76: =SUM(N75) -> 0 | O76: =SUM(O75:O75) -> 30000000
B78: Staff Event
B79: Customer Service Week | L79: =3193500+(3193500*0.29) -> 4119615 | O79: =SUM(I79:N79) -> 4119615
B80: Staff end of the year Party | N80: =20000000+(20000000*0.29) -> 25800000 | O80: =SUM(I80:N80) -> 25800000
B81: Total | C81: =SUM(C79:C80) -> 0 | D81: =SUM(D79:D80) -> 0 | E81: =SUM(E79:E80) -> 0 | F81: =SUM(F79:F80) -> 0 | G81: =SUM(G79:G80) -> 0 | H81: =SUM(H79:H80) -> 0 | I81: =SUM(I79:I80) -> 0 | J81: =SUM(J79:J80) -> 0 | ... O81: =SUM(O79:O80) -> 29919615
B83: Funmigation & Consultatants | O83: =D84+(D84*0.29) -> 0
B84: Funmigation | C84: =300000+(300000*0.5) -> 450000 | H84: =C84+(C84*0.29) -> 580500 | O84: =SUM(C84:N84) -> 1030500
B85: Consultants | E85: 5000000 | H85: 5000000 | K85: 5000000 | O85: =SUM(C85:N85) -> 15000000
B86: Total | C86: =SUM(C84:C85) -> 450000 | D86: =SUM(D84:D85) -> 0 | E86: =SUM(E84:E85) -> 5000000 | F86: =SUM(F84:F85) -> 0 | G86: =SUM(G84:G85) -> 0 | H86: =SUM(H84:H85) -> 5580500 | I86: =SUM(I84:I85) -> 0 | J86: =SUM(J84:J85) -> 0 | ... O86: =SUM(O84:O85) -> 16030500
B87: Travelling Expenses | O87: =SUM(C87:N87) -> 0
B88: Flight Ticket | C88: 5000000 | D88: 5000000 | E88: 5000000 | F88: 10000000 | G88: 10000000 | H88: 10000000 | I88: 20000000 | J88: 20000000 | K88: 20000000 | L88: 30000000 | M88: 30000000 | N88: 30000000 | O88: =SUM(C88:N88) -> 195000000
B89: Hotel Reservations | C89: 1000000 | D89: 1000000 | E89: 1000000 | F89: 5000000 | G89: 5000000 | H89: 5000000 | I89: 10000000 | J89: 10000000 | K89: 10000000 | L89: 15000000 | M89: 15000000 | N89: 15000000 | O89: =SUM(C89:N89) -> 93000000
B90: Logistics | C90: 500000 | D90: 500000 | E90: 500000 | F90: 1000000 | G90: 1000000 | H90: 1000000 | I90: 1500000 | J90: 1500000 | K90: 1500000 | L90: 2000000 | M90: 2000000 | N90: 2000000 | O90: =SUM(C90:N90) -> 15000000
B91: Feeding | C91: 500000 | D91: 500000 | E91: 500000 | F91: 600000 | G91: 600000 | H91: 600000 | I91: 700000 | J91: 700000 | K91: 700000 | L91: 800000 | M91: 800000 | N91: 800000 | O91: =SUM(C91:N91) -> 7800000
B92: Total | C92: =SUM(C88:C91) -> 7000000 | D92: =SUM(D88:D91) -> 7000000 | E92: =SUM(E88:E91) -> 7000000 | F92: =SUM(F88:F91) -> 16600000 | G92: =SUM(G88:G91) -> 16600000 | H92: =SUM(H88:H91) -> 16600000 | I92: =SUM(I88:I91) -> 32200000 | J92: =SUM(J88:J91) -> 32200000 | ... O92: =SUM(O88:O91) -> 310800000

Sheet Comments and Notes
C3: The 24.98% inflation rate forecasted is based on Statistica's inflation forecast for 2025
C5: Communication Expense | D5: Comments/Note
C6: Airtime and Data
C7: CUG Subscription
C8: Office Internet
C9: Total
C11: Personnel Expenses
C12: Salaries and Allowance | D12: As at December 2024, the budget was N9,983,880.10. We included the net salary for the following roles: lead ICA, Financial Controller, BDC Officer, Finance Officer in January 2025 while HR/Admin Officer and Corporate Comms Officer. Key account managers (senior and junior), T.A and E.A were added in February 2025. We budgeted 243,000 in July for 3 corp. members at 81,000 each.
C13: Leave Allowance | D13: This is computed using 10% of the annual basic salary.
C14: Bonus | D14: The maximum performance bonus is 100% gross for each quarter, which is paid in the following month. Only confirmed employees are eligible and we factored in the number of eligible employees per quarter.
C15: 13th Month Salary | D15: 100% of employee gross salary payable in December
C16: Promotion | D16: Promotion is subject to performance. We calculated a 50% increment and added the sum of 3,000,000 to cover promotion to higher levels.
C17: Staff end of the year package | D17: We factored in a total of 15 new employees and adjusted the gifts according to their projected level. According to Statistica, the inflation rate for 2025 is 24.98%. We marked up using this percentage.
C18: Staff Training and development | D18: We budgeted N400,000 per employee per quarter. We are working with a total of 64 employees while factoring in special trainings in specific months.
C19: New Staff Salary | D19: The projection is based on the number of expected employees per month.
C20: Long service award | D20: Ayodele and titi will be paid N50,000 each for completing 5 years in 2024 while Damilola will be paid in June 2025.
C21: Drivers' Salary | D21: Each driver earns N112,801 monthly gross while the executive drivers earn N173,6725 monthly gross. We currently have 9 drivers and will be ionboarding 3 in February and 1 staff bus driver in April 2025.
C22: NSITF | D22: 1% of annual payroll
C23: ITF | D23: 1% of annual payroll
... C27: Transportation Allowance | D27: The sum of N40,000 is paid monthly to staff to auugment transportation expenses. This calculation was done based on the number of employees to be onboarded monthly.
C28: Total
C30: Insurance
C31: Hmo | D31: The Platinum plan costs N570236 (4 individuals are entitled to this). The corporate silver plan costs N99,873
C32: Group Life | D32: The premium is calculated as sum insured *3 of the annual salaries for each staff multiplied by 0.06.
C33: Fire & Buglary | D33: The premium is N353,369 and a 30% inflation rate was factored in.
C34: Vehicle | D34: We budgeted based on the insurance renewal dates of the existing vehicles and factored in the insurance renewal date for the staff bus in december.
C35: Total
C38: Sport and Fitness
C39: Field usage and aerobics | D39: We budgeted N350,000 monthly for field usage and added N100,000 payment to the aerobics instructor.
C40: Entertainment | D40: We considered the fact that aerobics and football training will be combined to determine that N350,000 would cover entertainment per week.
C41: Players Logistics | D41: This cost covers transportation fare given to the external players (N100,000) and purchase of training items such as boots etc.
C42: Total
C45: Repairs and Maintenance
C46: Vehicle Repairs | D46: We projected that the sum of N300,000 would be expended on vehicle repairs monthly for Q1, while N500,000 would be expended monthly for Q2 and Q3 and finally, N750000 would be expended in Q4
C47: Motor Vehicle Renewal | D47: Renewal of vehicle documents cost N21,000. In January, it is projected that we would acquire at least 5 new vehicles and the cost of registration was factored in, in January. We also considered the expiry date of the licences of existing vehicles.
C48: Vehicle Maintenance | D48: We budgeted the sum of N300,000 for vehicle maintenance in Q1 and Q2. This was increased to N500,000 in Q3 because we anticipate that there will be need to do more repairs toward the end of the year. We also factored in N1000000 in Q4 to also cover maintenance cost for new vehicles.
C49: Total
C52: Rent Related
C53: Annual Rent | D53: In 2024, our rent was increased to 17,199,000 per annum which is expected to be paid by June 1, 2025. We also prohjected that there will be need to rent a new office space and budgeted the sum of N30,000,000 to cover rent for the new office.
C54: Sevice charges (annually) | D54: The service charge was increased in 2025 to 1,782,656.78 and this would be paid along with the rent due in June 2025. We also budgeted the sum of N2,500,000.00 as service charge for the new office.
C55: Electricity supply charges (Quarterly ) | D55: The electricity charge for November 2024 was N717,559.56. This charge was marked up to N800,000 per month and N2,400,000 per quarter with a 20% increase every quarter.
C56: Total
C59: Birthday Gift
C60: Staff Gift | D60: We project that the sum of N40,000 would be expended on individual birthday cakes in 2025. The computation was done based on the birthday dates of current staff and in September, we included the birthday cakes of 28 new employees.
C61: Total
C63: Fuelling
C64: Pool Car | D64: The pool car is fueled with 200,000 monthly and a 35% inflation rate was factored quarterly
C65: MD's Car | D65: The MD's car is fueled with 1500,000 monthly and a 35% inflation rate was factored quarterly
C66: Official Car | D66: The fuel allowance for the Official's vechicle is 100,000 for two staff making a total of 200,000 monthly and 35% inflation rate was factored quarterly
C67: BDM's Car | D67: The fuel allowance for the BDM's vechicle is 100,000 monthly
C68: Total
C70: Team Bonding
C71: Weekly Lunch | D71: The projected number of staff for SIL is 35. Currently employees receives 3,000 lucnch allowance three times a week (Monday, Wednesday and Friday).
C72: Quarterly Team Bonding | D72: The projected number of staff for SIL is 35 and for SFCL IS 20 making a total of 55 employees. It is 45,000 per employee every last Friday of the quarter.
C73: Total
C75: General Office Expense
C76: Stationery | D76: The cost for 57 employees and 20% inflation rate was factored
C77: Printables | D77: This includes printing ofLetter head @70,000, 100 Envelop @#50,000, M.D's Complimentary card @75,000 and ID cards for 34 staff @ 10000 (N340000)
C78: Office supplies and Provisions | D78: The cost for 35 employees is 700,000.00 and a 35% inflation rate was factored
C79: Total
C81: Training and Team Building
C82: Strategy Retreat | D82: We budgeted the sum of N30,000,000 to cover 2 strategy retreats in 2025 bringing it to a total of N60,000,000.
C83: Total
C85: Staff Event
C86: Customer Service Week | D86: We expended a total of N3,193,500 for CSW in 2024. This amount was marked up by 29%.
C87: Staff end of the year Party | D87: We marked up the 2024 budget of 20,000,000 by 29%
C88: Total
C90: Funmigation | D90: We plan to carry out funmigation exercise twice in a year. The sum of 450,000 was budgeted to cover funmigation and cleaning in January while that sum was marked up by 29% for the half year funmigation and cleaning.
C91: Consultants | D91: We budgeted 5,000,000 per quarter to cover consultants' fee.
C92: Travelling Expenses
C93: Flight Ticket | D93: This budget considered the possibility of frequent work-related travels abroad and within nigeria
C94: Hotel and Reservations | D94: We increased the budget for hotel accomodations for 2025 due to the possibility of more frequent work-related travels in 2025.
C95: Logistics | D95: This covers movement within the travel destination
C96: Feeding | D96: A markup was done to cover feeding expenses.
C97: Capital Expenditure | D97: We budgeted the sum of N43,000,000 to purchase 4 vehicles in January.

Sheet Employer's Pension (New Staff)
A3: Roles | B3: Projected Salary | C3: Pension
A4: T.A | B4: 346818.85 | C4: 14060.22
A5: ICA | B5: 603693.01 | C5: 28630.8
A6: Front Desk | B6: 266175 | C6: 10647
A7: Corp. Comms | B7: 346818.85 | C7: 14060.22
A8: Finance Officer | B8: 266175 | C8: 10647
A9: Account Manager 1 | B9: 266175 | C9: 10647
A10: Account Manager 2 | B10: 346818.85 | C10: 14060.22
A11: I.T | B11: 266175 | C11: 10647
A12: Driver | B12: 110565
A13: Driver | B13: 110565
A14: Total | B14: =SUM(B4:B13) -> 2929979.6 | C14: =SUM(C4:C13) -> 113399.46
C15: 313050.32
C16: =SUM(C14:C15) -> 426449.78

Sheet Capital Expenditure
B2: Assets | C2: January | D2: February | E2: March | F2: April | G2: May | H2: June | I2: July | J2: August | K2: September | L2: October | M2: November | N2: December | O2: Total
O3: ₦
B4: Motor Vehicle | O4: =SUM(C4:N4) -> 0
B5: File Cabinet | O5: =SUM(C5:N5) -> 0
B6: Furniture and Fittings | O6: =SUM(C6:N6) -> 0
O7: =SUM(C7:N7) -> 0
O8: =SUM(C8:N8) -> 0
B9: Total | C9: =SUM(C4:C8) -> 0 | D9: =SUM(D4:D8) -> 0 | E9: =SUM(E4:E8) -> 0 | F9: =SUM(F4:F8) -> 0 | G9: =SUM(G4:G8) -> 0 | H9: =SUM(H4:H8) -> 0 | I9: =SUM(I4:I8) -> 0 | J9: =SUM(J4:J8) -> 0 | ... O9: =SUM(O4:O8) -> 0
